AndroidAnquanBijiJnusimba/README.md
AndroidAnquanBijiJnusimba/__init__.py
AndroidAnquanBijiJnusimba/__main__.py
AndroidAnquanBijiJnusimba/file.epub
AndroidAnquanBijiJnusimba/index.html
AndroidAnquanBijiJnusimba/css/__init__.py
AndroidAnquanBijiJnusimba/css/annotations.css
AndroidAnquanBijiJnusimba/css/main.css
AndroidAnquanBijiJnusimba/css/normalize.css
AndroidAnquanBijiJnusimba/css/popup.css
AndroidAnquanBijiJnusimba/font/__init__.py
AndroidAnquanBijiJnusimba/font/fontello.eot
AndroidAnquanBijiJnusimba/font/fontello.svg
AndroidAnquanBijiJnusimba/font/fontello.ttf
AndroidAnquanBijiJnusimba/font/fontello.woff
AndroidAnquanBijiJnusimba/img/__init__.py
AndroidAnquanBijiJnusimba/img/annotator-glyph-sprite.png
AndroidAnquanBijiJnusimba/img/annotator-icon-sprite.png
AndroidAnquanBijiJnusimba/img/apple-touch-icon.png
AndroidAnquanBijiJnusimba/img/cancelfullscreen.png
AndroidAnquanBijiJnusimba/img/close.png
AndroidAnquanBijiJnusimba/img/fullscreen.png
AndroidAnquanBijiJnusimba/img/loader.gif
AndroidAnquanBijiJnusimba/img/menu-icon.png
AndroidAnquanBijiJnusimba/img/save.png
AndroidAnquanBijiJnusimba/img/saved.png
AndroidAnquanBijiJnusimba/img/settings-s.png
AndroidAnquanBijiJnusimba/img/settings.png
AndroidAnquanBijiJnusimba/img/star.png
AndroidAnquanBijiJnusimba/js/__init__.py
AndroidAnquanBijiJnusimba/js/epub.js
AndroidAnquanBijiJnusimba/js/epub.min.js
AndroidAnquanBijiJnusimba/js/epub.min.map
AndroidAnquanBijiJnusimba/js/hooks.min.js
AndroidAnquanBijiJnusimba/js/hooks.min.map
AndroidAnquanBijiJnusimba/js/reader.js
AndroidAnquanBijiJnusimba/js/reader.js.map
AndroidAnquanBijiJnusimba/js/reader.min.js
AndroidAnquanBijiJnusimba/js/reader.min.map
AndroidAnquanBijiJnusimba/js/hooks/__init__.py
AndroidAnquanBijiJnusimba/js/hooks/extensions/__init__.py
AndroidAnquanBijiJnusimba/js/hooks/extensions/highlight.js
AndroidAnquanBijiJnusimba/js/libs/__init__.py
AndroidAnquanBijiJnusimba/js/libs/jquery.min.js
AndroidAnquanBijiJnusimba/js/libs/localforage.min.js
android_anquan_biji_jnusimba-2024.3.3.0.dist-info/METADATA
android_anquan_biji_jnusimba-2024.3.3.0.dist-info/WHEEL
android_anquan_biji_jnusimba-2024.3.3.0.dist-info/entry_points.txt
android_anquan_biji_jnusimba-2024.3.3.0.dist-info/top_level.txt
android_anquan_biji_jnusimba-2024.3.3.0.dist-info/RECORD
